llmobserve/INSTRUMENTORS_STATUS.md
llmobserve/__init__.py
llmobserve/agent_detector.py
llmobserve/agent_wrapper.py
llmobserve/ai_instrument.py
llmobserve/buffer.py
llmobserve/caps.py
llmobserve/celery_support.py
llmobserve/cli.py
llmobserve/config.py
llmobserve/context.py
llmobserve/decorators.py
llmobserve/distributed.py
llmobserve/event_creator.py
llmobserve/framework_auto_patch.py
llmobserve/framework_hooks.py
llmobserve/grpc_costs.py
llmobserve/grpc_interceptor.py
llmobserve/http_fallback.py
llmobserve/http_interceptor.py
llmobserve/middleware.py
llmobserve/multi_language_analyzer.py
llmobserve/observe.py
llmobserve/openai_patch.py
llmobserve/patcher.py
llmobserve/pinecone_patch.py
llmobserve/pricing.py
llmobserve/proxy_manager.py
llmobserve/refiner.py
llmobserve/request_tracker.py
llmobserve/retry_tracking.py
llmobserve/robustness.py
llmobserve/scanner.py
llmobserve/semantic_mapper.py
llmobserve/static_analyzer.py
llmobserve/tool_wrapper.py
llmobserve/transport.py
llmobserve/types.py
llmobserve/websocket_interceptor.py
llmobserve/instrumentation/__init__.py
llmobserve/instrumentation/anthropic_instrumentor.py
llmobserve/instrumentation/assemblyai_instrumentor.py
llmobserve/instrumentation/azure_speech_instrumentor.py
llmobserve/instrumentation/bland_instrumentor.py
llmobserve/instrumentation/cartesia_instrumentor.py
llmobserve/instrumentation/cohere_instrumentor.py
llmobserve/instrumentation/deepgram_instrumentor.py
llmobserve/instrumentation/elevenlabs_instrumentor.py
llmobserve/instrumentation/gladia_instrumentor.py
llmobserve/instrumentation/google_instrumentor.py
llmobserve/instrumentation/google_stt_instrumentor.py
llmobserve/instrumentation/livekit_instrumentor.py
llmobserve/instrumentation/openai_instrumentor.py
llmobserve/instrumentation/openai_realtime_instrumentor.py
llmobserve/instrumentation/pinecone_instrumentor.py
llmobserve/instrumentation/playht_instrumentor.py
llmobserve/instrumentation/retell_instrumentor.py
llmobserve_sdk-0.3.7.dist-info/METADATA
llmobserve_sdk-0.3.7.dist-info/WHEEL
llmobserve_sdk-0.3.7.dist-info/entry_points.txt
llmobserve_sdk-0.3.7.dist-info/top_level.txt
llmobserve_sdk-0.3.7.dist-info/RECORD
