Metadata-Version: 2.4
Name: llmobserve-sdk
Version: 0.3.7
Summary: Automatic cost tracking and observability for LLM applications
Home-page: https://github.com/yourusername/llmobserve
Author: Pranav Srigiriraju
Author-email: Pranav Srigiriraju <support@llmobserve.com>
License: MIT
Project-URL: Homepage, https://llmobserve.com
Project-URL: Documentation, https://app.llmobserve.com/docs
Project-URL: Repository, https://github.com/pss9179/CostTracking
Keywords: llm,observability,cost-tracking,openai,monitoring
Classifier: Development Status :: 4 - Beta
Classifier: Intended Audience :: Developers
Classifier: Topic :: Software Development :: Libraries :: Python Modules
Classifier: License :: OSI Approved :: MIT License
Classifier: Programming Language :: Python :: 3
Classifier: Programming Language :: Python :: 3.8
Classifier: Programming Language :: Python :: 3.9
Classifier: Programming Language :: Python :: 3.10
Classifier: Programming Language :: Python :: 3.11
Classifier: Programming Language :: Python :: 3.12
Requires-Python: >=3.8
Requires-Dist: tiktoken>=0.5.0
Requires-Dist: certifi>=2023.0.0
Provides-Extra: dev
Requires-Dist: pytest>=7.0.0; extra == "dev"
Requires-Dist: pytest-asyncio>=0.21.0; extra == "dev"
Requires-Dist: black>=23.0.0; extra == "dev"
Requires-Dist: mypy>=1.0.0; extra == "dev"
Dynamic: author
Dynamic: home-page
Dynamic: requires-python
